TPI.cpython-39-darwin.so
tpi_splines-1.0.1.dist-info/METADATA
tpi_splines-1.0.1.dist-info/WHEEL
tpi_splines-1.0.1.dist-info/top_level.txt
tpi_splines-1.0.1.dist-info/RECORD
