Metadata-Version: 2.1
Name: tpi-splines
Version: 1.0.1
Summary: Tensor product spline interpolation package
Home-page: https://github.com/mpuerrer/TPI
Author: Michael Pürrer, Jonathan Blackman
Author-email: "Michael Pürrer, Jonathan Blackman" <Michael.Puerrer@gmail.com>
Project-URL: Homepage, https://github.com/mpuerrer/TPI
Keywords: feed,reader,tutorial
Classifier: Development Status :: 5 - Production/Stable
Classifier: Intended Audience :: Science/Research
Classifier: License :: OSI Approved :: GNU General Public License v3 (GPLv3)
Classifier: Programming Language :: Cython
Classifier: Programming Language :: Python
Classifier: Programming Language :: Python :: Implementation :: CPython
Classifier: Programming Language :: Python :: 3
Classifier: Topic :: Scientific/Engineering
Classifier: Operating System :: Unix
Classifier: Operating System :: POSIX :: Linux
Classifier: Operating System :: MacOS :: MacOS X
Requires-Python: >=3.0
Requires-Dist: numpy (>=1.11)
Provides-Extra: dev
Requires-Dist: pytest ; extra == 'dev'
